{"matchId_EUW1_7016496140": {"participant_1": {"role_SUPPORT": {"teamId_100": {"position_UTILITY": {"minutes": {"0": "Current-Gold : 500, Level : 1, CS : 0, Total-Gold : 500, JungleMinionsKilled : 0, Kills : 0, Deaths : 0, Assists : 0, ", "1": "Current-Gold : 0, Level : 1, CS : 0, Total-Gold : 500, JungleMinionsKilled : 0, Kills : 0, Deaths : 0, Assists : 0, ", "2": "Current-Gold : 46, Level : 1, CS : 0, Total-Gold : 546, JungleMinionsKilled : 0, Kills : 0, Deaths : 0, Assists : 0, ", "3": "Current-Gold : 223, Level : 2, CS : 1, Total-Gold : 723, JungleMinionsKilled : 0, Kills : 0, Deaths : 0, Assists : 0, ", "4": "Current-Gold : 430, Level : 2, CS : 2, Total-Gold : 930, JungleMinionsKilled : 0, Kills : 0, Deaths : 0, Assists : 0, ", "5": "Current-Gold : 67, Level : 3, CS : 2, Total-Gold : 1092, JungleMinionsKilled : 0, Kills : 0, Deaths : 0, Assists : 0, ", "6": "Current-Gold : 274, Level : 3, CS : 2, Total-Gold : 1299, JungleMinionsKilled : 0, Kills : 0, Deaths : 0, Assists : 0, ", "7": "Current-Gold : 607, Level : 4, CS : 4, Total-Gold : 1632, JungleMinionsKilled : 0, Kills : 0, Deaths : 1, Assists : 0, ", "8": "Current-Gold : 225, Level : 4, CS : 7, Total-Gold : 1850, JungleMinionsKilled : 0, Kills : 0, Deaths : 1, Assists : 1, ", "9": "Current-Gold : 570, Level : 5, CS : 8, Total-Gold : 2275, JungleMinionsKilled : 0, Kills : 0, Deaths : 2, Assists : 1, ", "10": "Current-Gold : 1007, Level : 5, CS : 8, Total-Gold : 2712, JungleMinionsKilled : 0, Kills : 0, Deaths : 3, Assists : 2, ", "11": "Current-Gold : 358, Level : 5, CS : 8, Total-Gold : 2938, JungleMinionsKilled : 0, Kills : 0, Deaths : 3, Assists : 4, ", "12": "Current-Gold : 703, Level : 6, CS : 11, Total-Gold : 3283, JungleMinionsKilled : 0, Kills : 0, Deaths : 3, Assists : 4, ", "13": "Current-Gold : 193, Level : 6, CS : 13, Total-Gold : 3578, JungleMinionsKilled : 0, Kills : 0, Deaths : 3, Assists : 5, ", "14": "Current-Gold : 95, Level : 7, CS : 13, Total-Gold : 3880, JungleMinionsKilled : 0, Kills : 0, Deaths : 3, Assists : 5, ", "15": "Current-Gold : 426, Level : 7, CS : 14, Total-Gold : 4216, JungleMinionsKilled : 0, Kills : 0, Deaths : 4, Assists : 6, ", "16": "Current-Gold : 770, Level : 8, CS : 14, Total-Gold : 4560, JungleMinionsKilled : 0, Kills : 0, Deaths : 4, Assists : 7, "}}}}}, "participant_2": {"role_SUPPORT": {"teamId_100": {"position_JUNGLE": {"minutes": {"0": "Current-Gold : 500, Level : 1, CS : 0, Total-Gold : 500, JungleMinionsKilled : 0, Kills : 0, Deaths : 0, Assists : 0, ", "1": "Current-Gold : 0, Level : 1, CS : 0, Total-Gold : 500, JungleMinionsKilled : 0, Kills : 0, Deaths : 0, Assists : 0, ", "2": "Current-Gold : 111, Level : 2, CS : 0, Total-Gold : 611, JungleMinionsKilled : 4, Kills : 0, Deaths : 0, Assists : 0, ", "3": "Current-Gold : 493, Level : 3, CS : 0, Total-Gold : 993, JungleMinionsKilled : 16, Kills : 0, Deaths : 0, Assists : 0, ", "4": "Current-Gold : 968, Level : 4, CS : 0, Total-Gold : 1468, JungleMinionsKilled : 24, Kills : 0, Deaths : 0, Assists : 0, ", "5": "Current-Gold : 71, Level : 4, CS : 0, Total-Gold : 1821, JungleMinionsKilled : 28, Kills : 0, Deaths : 0, Assists : 1, ", "6": "Current-Gold : 170, Level : 5, CS : 2, Total-Gold : 2170, JungleMinionsKilled : 36, Kills : 0, Deaths : 0, Assists : 2, ", "7": "Current-Gold : 760, Level : 6, CS : 2, Total-Gold : 2760, JungleMinionsKilled : 44, Kills : 0, Deaths : 1, Assists : 2, ", "8": "Current-Gold : 232, Level : 6, CS : 2, Total-Gold : 3182, JungleMinionsKilled : 44, Kills : 1, Deaths : 1, Assists : 2, ", "9": "Current-Gold : 778, Level : 7, CS : 2, Total-Gold : 3728, JungleMinionsKilled : 61, Kills : 2, Deaths : 2, Assists : 2, ", "10": "Current-Gold : 1458, Level : 8, CS : 3, Total-Gold : 4408, JungleMinionsKilled : 68, Kills : 2, Deaths : 2, Assists : 2, ", "11": "Current-Gold : 102, Level : 8, CS : 3, Total-Gold : 4652, JungleMinionsKilled : 72, Kills : 3, Deaths : 2, Assists : 3, ", "12": "Current-Gold : 679, Level : 8, CS : 4, Total-Gold : 5229, JungleMinionsKilled : 78, Kills : 3, Deaths : 3, Assists : 3, ", "13": "Current-Gold : 1182, Level : 9, CS : 4, Total-Gold : 5732, JungleMinionsKilled : 94, Kills : 4, Deaths : 3, Assists : 3, ", "14": "Current-Gold : 88, Level : 10, CS : 9, Total-Gold : 5938, JungleMinionsKilled : 94, Kills : 4, Deaths : 3, Assists : 3, ", "15": "Current-Gold : 731, Level : 10, CS : 9, Total-Gold : 6581, JungleMinionsKilled : 102, Kills : 4, Deaths : 3, Assists : 3, ", "16": "Current-Gold : 1131, Level : 11, CS : 12, Total-Gold : 6986, JungleMinionsKilled : 102, Kills : 5, Deaths : 3, Assists : 3, "}}}}}, "participant_3": {"role_SUPPORT": {"teamId_100": {"position_MIDDLE": {"minutes": {"0": "Current-Gold : 500, Level : 1, CS : 0, Total-Gold : 500, JungleMinionsKilled : 0, Kills : 0, Deaths : 0, Assists : 0, ", "1": "Current-Gold : 0, Level : 1, CS : 0, Total-Gold : 500, JungleMinionsKilled : 0, Kills : 0, Deaths : 0, Assists : 0, ", "2": "Current-Gold : 77, Level : 1, CS : 3, Total-Gold : 577, JungleMinionsKilled : 0, Kills : 0, Deaths : 0, Assists : 0, ", "3": "Current-Gold : 413, Level : 3, CS : 13, Total-Gold : 913, JungleMinionsKilled : 0, Kills : 0, Deaths : 0, Assists : 0, ", "4": "Current-Gold : 433, Level : 4, CS : 21, Total-Gold : 1483, JungleMinionsKilled : 0, Kills : 0, Deaths : 0, Assists : 0, ", "5": "Current-Gold : 960, Level : 5, CS : 27, Total-Gold : 2010, JungleMinionsKilled : 0, Kills : 1, Deaths : 0, Assists : 0, ", "6": "Current-Gold : 943, Level : 5, CS : 33, Total-Gold : 2593, JungleMinionsKilled : 0, Kills : 2, Deaths : 0, Assists : 0, ", "7": "Current-Gold : 1344, Level : 6, CS : 43, Total-Gold : 2994, JungleMinionsKilled : 0, Kills : 3, Deaths : 1, Assists : 0, ", "8": "Current-Gold : 216, Level : 6, CS : 43, Total-Gold : 3566, JungleMinionsKilled : 0, Kills : 3, Deaths : 1, Assists : 1, ", "9": "Current-Gold : 586, Level : 7, CS : 54, Total-Gold : 3936, JungleMinionsKilled : 0, Kills : 4, Deaths : 2, Assists : 2, ", "10": "Current-Gold : 171, Level : 8, CS : 61, Total-Gold : 4621, JungleMinionsKilled : 0, Kills : 4, Deaths : 2, Assists : 2, ", "11": "Current-Gold : 712, Level : 8, CS : 72, Total-Gold : 5162, JungleMinionsKilled : 0, Kills : 5, Deaths : 3, Assists : 3, ", "12": "Current-Gold : 280, Level : 9, CS : 84, Total-Gold : 5663, JungleMinionsKilled : 0, Kills : 5, Deaths : 3, Assists : 3, ", "13": "Current-Gold : 580, Level : 9, CS : 93, Total-Gold : 5963, JungleMinionsKilled : 0, Kills : 5, Deaths : 3, Assists : 4, ", "14": "Current-Gold : 25, Level : 9, CS : 97, Total-Gold : 6448, JungleMinionsKilled : 0, Kills : 5, Deaths : 3, Assists : 4, ", "15": "Current-Gold : 392, Level : 10, CS : 107, Total-Gold : 6815, JungleMinionsKilled : 0, Kills : 6, Deaths : 4, Assists : 4, ", "16": "Current-Gold : 674, Level : 10, CS : 114, Total-Gold : 7097, JungleMinionsKilled : 0, Kills : 6, Deaths : 4, Assists : 4, "}}}}}, "participant_4": {"role_DUO": {"teamId_100": {"position_TOP": {"minutes": {"0": "Current-Gold : 500, Level : 1, CS : 0, Total-Gold : 500, JungleMinionsKilled : 0, Kills : 0, Deaths : 0, Assists : 0, ", "1": "Current-Gold : 0, Level : 1, CS : 0, Total-Gold : 500, JungleMinionsKilled : 0, Kills : 0, Deaths : 0, Assists : 0, ", "2": "Current-Gold : 21, Level : 1, CS : 0, Total-Gold : 521, JungleMinionsKilled : 0, Kills : 0, Deaths : 0, Assists : 0, ", "3": "Current-Gold : 141, Level : 3, CS : 5, Total-Gold : 1141, JungleMinionsKilled : 0, Kills : 0, Deaths : 0, Assists : 0, ", "4": "Current-Gold : 855, Level : 4, CS : 20, Total-Gold : 1855, JungleMinionsKilled : 0, Kills : 1, Deaths : 1, Assists : 0, ", "5": "Current-Gold : 180, Level : 5, CS : 29, Total-Gold : 2180, JungleMinionsKilled : 0, Kills : 2, Deaths : 1, Assists : 0, ", "6": "Current-Gold : 1074, Level : 6, CS : 47, Total-Gold : 3074, JungleMinionsKilled : 0, Kills : 2, Deaths : 1, Assists : 0, ", "7": "Current-Gold : 470, Level : 7, CS : 53, Total-Gold : 3345, JungleMinionsKilled : 0, Kills : 3, Deaths : 1, Assists : 0, ", "8": "Current-Gold : 1142, Level : 8, CS : 68, Total-Gold : 4017, JungleMinionsKilled : 0, Kills : 3, Deaths : 1, Assists : 0, ", "9": "Current-Gold : 283, Level : 8, CS : 78, Total-Gold : 4373, JungleMinionsKilled : 0, Kills : 3, Deaths : 1, Assists : 0, ", "10": "Current-Gold : 712, Level : 9, CS : 88, Total-Gold : 4802, JungleMinionsKilled : 0, Kills : 3, Deaths : 1, Assists : 0, ", "11": "Current-Gold : 2333, Level : 10, CS : 103, Total-Gold : 6423, JungleMinionsKilled : 0, Kills : 3, Deaths : 1, Assists : 0, ", "12": "Current-Gold : 761, Level : 11, CS : 118, Total-Gold : 7151, JungleMinionsKilled : 4, Kills : 5, Deaths : 1, Assists : 0, ", "13": "Current-Gold : 2077, Level : 11, CS : 131, Total-Gold : 8467, JungleMinionsKilled : 8, Kills : 6, Deaths : 1, Assists : 0, ", "14": "Current-Gold : 70, Level : 11, CS : 135, Total-Gold : 8660, JungleMinionsKilled : 8, Kills : 7, Deaths : 1, Assists : 0, ", "15": "Current-Gold : 515, Level : 12, CS : 149, Total-Gold : 9110, JungleMinionsKilled : 8, Kills : 7, Deaths : 1, Assists : 0, ", "16": "Current-Gold : 1379, Level : 12, CS : 151, Total-Gold : 9974, JungleMinionsKilled : 8, Kills : 7, Deaths : 1, Assists : 0, "}}}}}, "participant_5": {"role_SUPPORT": {"teamId_100": {"position_BOTTOM": {"minutes": {"0": "Current-Gold : 500, Level : 1, CS : 0, Total-Gold : 500, JungleMinionsKilled : 0, Kills : 0, Deaths : 0, Assists : 0, ", "1": "Current-Gold : 0, Level : 1, CS : 0, Total-Gold : 500, JungleMinionsKilled : 0, Kills : 0, Deaths : 0, Assists : 0, ", "2": "Current-Gold : 77, Level : 1, CS : 3, Total-Gold : 577, JungleMinionsKilled : 0, Kills : 0, Deaths : 0, Assists : 0, ", "3": "Current-Gold : 47, Level : 2, CS : 18, Total-Gold : 997, JungleMinionsKilled : 0, Kills : 0, Deaths : 0, Assists : 0, ", "4": "Current-Gold : 266, Level : 3, CS : 23, Total-Gold : 1216, JungleMinionsKilled : 0, Kills : 0, Deaths : 0, Assists : 0, ", "5": "Current-Gold : 674, Level : 4, CS : 36, Total-Gold : 1624, JungleMinionsKilled : 0, Kills : 0, Deaths : 0, Assists : 0, ", "6": "Current-Gold : 1386, Level : 6, CS : 49, Total-Gold : 2336, JungleMinionsKilled : 0, Kills : 0, Deaths : 0, Assists : 0, ", "7": "Current-Gold : 216, Level : 6, CS : 59, Total-Gold : 2666, JungleMinionsKilled : 0, Kills : 1, Deaths : 0, Assists : 0, ", "8": "Current-Gold : 674, Level : 7, CS : 71, Total-Gold : 3124, JungleMinionsKilled : 4, Kills : 1, Deaths : 0, Assists : 0, ", "9": "Current-Gold : 1432, Level : 8, CS : 83, Total-Gold : 3882, JungleMinionsKilled : 4, Kills : 1, Deaths : 0, Assists : 0, ", "10": "Current-Gold : 482, Level : 8, CS : 93, Total-Gold : 4182, JungleMinionsKilled : 4, Kills : 2, Deaths : 0, Assists : 0, ", "11": "Current-Gold : 227, Level : 9, CS : 99, Total-Gold : 4527, JungleMinionsKilled : 4, Kills : 2, Deaths : 0, Assists : 0, ", "12": "Current-Gold : 752, Level : 9, CS : 109, Total-Gold : 5052, JungleMinionsKilled : 4, Kills : 2, Deaths : 1, Assists : 0, ", "13": "Current-Gold : 156, Level : 9, CS : 118, Total-Gold : 5776, JungleMinionsKilled : 4, Kills : 2, Deaths : 1, Assists : 0, ", "14": "Current-Gold : 425, Level : 10, CS : 123, Total-Gold : 6045, JungleMinionsKilled : 4, Kills : 2, Deaths : 1, Assists : 0, ", "15": "Current-Gold : 626, Level : 11, CS : 141, Total-Gold : 6546, JungleMinionsKilled : 4, Kills : 2, Deaths : 1, Assists : 0, ", "16": "Current-Gold : 1987, Level : 11, CS : 148, Total-Gold : 7907, JungleMinionsKilled : 4, Kills : 2, Deaths : 1, Assists : 0, "}}}}}, "participant_6": {"role_SUPPORT": {"teamId_200": {"position_UTILITY": {"minutes": {"0": "Current-Gold : 500, Level : 1, CS : 0, Total-Gold : 500, JungleMinionsKilled : 0, Kills : 0, Deaths : 0, Assists : 0, ", "1": "Current-Gold : 0, Level : 1, CS : 0, Total-Gold : 500, JungleMinionsKilled : 0, Kills : 0, Deaths : 0, Assists : 0, ", "2": "Current-Gold : 51, Level : 1, CS : 0, Total-Gold : 551, JungleMinionsKilled : 0, Kills : 0, Deaths : 0, Assists : 0, ", "3": "Current-Gold : 243, Level : 2, CS : 2, Total-Gold : 743, JungleMinionsKilled : 0, Kills : 0, Deaths : 0, Assists : 0, ", "4": "Current-Gold : 450, Level : 3, CS : 2, Total-Gold : 950, JungleMinionsKilled : 0, Kills : 0, Deaths : 0, Assists : 0, ", "5": "Current-Gold : 656, Level : 3, CS : 2, Total-Gold : 1156, JungleMinionsKilled : 0, Kills : 0, Deaths : 0, Assists : 0, ", "6": "Current-Gold : 41, Level : 4, CS : 2, Total-Gold : 1641, JungleMinionsKilled : 0, Kills : 0, Deaths : 0, Assists : 0, ", "7": "Current-Gold : 151, Level : 4, CS : 5, Total-Gold : 1826, JungleMinionsKilled : 0, Kills : 0, Deaths : 1, Assists : 3, ", "8": "Current-Gold : 443, Level : 4, CS : 5, Total-Gold : 2118, JungleMinionsKilled : 0, Kills : 0, Deaths : 2, Assists : 3, ", "9": "Current-Gold : 267, Level : 5, CS : 5, Total-Gold : 2342, JungleMinionsKilled : 0, Kills : 0, Deaths : 2, Assists : 4, ", "10": "Current-Gold : 63, Level : 5, CS : 6, Total-Gold : 2538, JungleMinionsKilled : 0, Kills : 0, Deaths : 2, Assists : 5, ", "11": "Current-Gold : 718, Level : 6, CS : 6, Total-Gold : 3193, JungleMinionsKilled : 0, Kills : 0, Deaths : 3, Assists : 5, ", "12": "Current-Gold : 42, Level : 6, CS : 6, Total-Gold : 3417, JungleMinionsKilled : 0, Kills : 1, Deaths : 3, Assists : 5, ", "13": "Current-Gold : 209, Level : 6, CS : 7, Total-Gold : 3584, JungleMinionsKilled : 0, Kills : 1, Deaths : 3, Assists : 5, ", "14": "Current-Gold : 30, Level : 7, CS : 9, Total-Gold : 4080, JungleMinionsKilled : 0, Kills : 1, Deaths : 3, Assists : 5, ", "15": "Current-Gold : 248, Level : 7, CS : 9, Total-Gold : 4298, JungleMinionsKilled : 0, Kills : 1, Deaths : 3, Assists : 7, ", "16": "Current-Gold : 75, Level : 7, CS : 9, Total-Gold : 4425, JungleMinionsKilled : 0, Kills : 1, Deaths : 3, Assists : 7, "}}}}}, "participant_7": {"role_DUO": {"teamId_200": {"position_MIDDLE": {"minutes": {"0": "Current-Gold : 500, Level : 1, CS : 0, Total-Gold : 500, JungleMinionsKilled : 0, Kills : 0, Deaths : 0, Assists : 0, ", "1": "Current-Gold : 0, Level : 1, CS : 0, Total-Gold : 500, JungleMinionsKilled : 0, Kills : 0, Deaths : 0, Assists : 0, ", "2": "Current-Gold : 63, Level : 1, CS : 2, Total-Gold : 563, JungleMinionsKilled : 0, Kills : 0, Deaths : 0, Assists : 0, ", "3": "Current-Gold : 353, Level : 3, CS : 11, Total-Gold : 853, JungleMinionsKilled : 0, Kills : 0, Deaths : 0, Assists : 0, ", "4": "Current-Gold : 54, Level : 4, CS : 23, Total-Gold : 1204, JungleMinionsKilled : 0, Kills : 0, Deaths : 0, Assists : 0, ", "5": "Current-Gold : 309, Level : 4, CS : 28, Total-Gold : 1459, JungleMinionsKilled : 0, Kills : 0, Deaths : 1, Assists : 0, ", "6": "Current-Gold : 46, Level : 5, CS : 39, Total-Gold : 2546, JungleMinionsKilled : 0, Kills : 0, Deaths : 1, Assists : 0, ", "7": "Current-Gold : 486, Level : 6, CS : 54, Total-Gold : 2986, JungleMinionsKilled : 0, Kills : 2, Deaths : 1, Assists : 1, ", "8": "Current-Gold : 178, Level : 7, CS : 62, Total-Gold : 3903, JungleMinionsKilled : 0, Kills : 2, Deaths : 1, Assists : 1, ", "9": "Current-Gold : 611, Level : 8, CS : 77, Total-Gold : 4336, JungleMinionsKilled : 0, Kills : 4, Deaths : 2, Assists : 1, ", "10": "Current-Gold : 251, Level : 8, CS : 81, Total-Gold : 4526, JungleMinionsKilled : 0, Kills : 4, Deaths : 2, Assists : 1, ", "11": "Current-Gold : 1109, Level : 9, CS : 88, Total-Gold : 5384, JungleMinionsKilled : 0, Kills : 4, Deaths : 3, Assists : 1, ", "12": "Current-Gold : 137, Level : 9, CS : 91, Total-Gold : 5562, JungleMinionsKilled : 0, Kills : 5, Deaths : 3, Assists : 1, ", "13": "Current-Gold : 415, Level : 9, CS : 100, Total-Gold : 5845, JungleMinionsKilled : 0, Kills : 5, Deaths : 4, Assists : 1, ", "14": "Current-Gold : 458, Level : 10, CS : 112, Total-Gold : 6238, JungleMinionsKilled : 0, Kills : 5, Deaths : 4, Assists : 1, ", "15": "Current-Gold : 874, Level : 10, CS : 125, Total-Gold : 6654, JungleMinionsKilled : 0, Kills : 5, Deaths : 5, Assists : 1, ", "16": "Current-Gold : 986, Level : 10, CS : 125, Total-Gold : 6766, JungleMinionsKilled : 0, Kills : 5, Deaths : 5, Assists : 1, "}}}}}, "participant_8": {"role_SUPPORT": {"teamId_200": {"position_JUNGLE": {"minutes": {"0": "Current-Gold : 500, Level : 1, CS : 0, Total-Gold : 500, JungleMinionsKilled : 0, Kills : 0, Deaths : 0, Assists : 0, ", "1": "Current-Gold : 50, Level : 1, CS : 0, Total-Gold : 500, JungleMinionsKilled : 0, Kills : 0, Deaths : 0, Assists : 0, ", "2": "Current-Gold : 241, Level : 2, CS : 0, Total-Gold : 691, JungleMinionsKilled : 8, Kills : 0, Deaths : 0, Assists : 0, ", "3": "Current-Gold : 714, Level : 4, CS : 0, Total-Gold : 1164, JungleMinionsKilled : 23, Kills : 0, Deaths : 0, Assists : 0, ", "4": "Current-Gold : 865, Level : 4, CS : 0, Total-Gold : 1315, JungleMinionsKilled : 24, Kills : 0, Deaths : 0, Assists : 0, ", "5": "Current-Gold : 168, Level : 4, CS : 0, Total-Gold : 1518, JungleMinionsKilled : 28, Kills : 0, Deaths : 0, Assists : 0, ", "6": "Current-Gold : 932, Level : 5, CS : 2, Total-Gold : 2282, JungleMinionsKilled : 38, Kills : 0, Deaths : 1, Assists : 0, ", "7": "Current-Gold : 1243, Level : 5, CS : 3, Total-Gold : 2598, JungleMinionsKilled : 42, Kills : 1, Deaths : 1, Assists : 1, ", "8": "Current-Gold : 1726, Level : 6, CS : 3, Total-Gold : 3081, JungleMinionsKilled : 50, Kills : 1, Deaths : 1, Assists : 1, ", "9": "Current-Gold : 240, Level : 6, CS : 3, Total-Gold : 3270, JungleMinionsKilled : 50, Kills : 1, Deaths : 1, Assists : 3, ", "10": "Current-Gold : 796, Level : 7, CS : 5, Total-Gold : 3831, JungleMinionsKilled : 54, Kills : 1, Deaths : 1, Assists : 4, ", "11": "Current-Gold : 1269, Level : 7, CS : 7, Total-Gold : 4314, JungleMinionsKilled : 62, Kills : 2, Deaths : 1, Assists : 4, ", "12": "Current-Gold : 1637, Level : 8, CS : 12, Total-Gold : 4682, JungleMinionsKilled : 66, Kills : 2, Deaths : 1, Assists : 5, ", "13": "Current-Gold : 284, Level : 8, CS : 13, Total-Gold : 4934, JungleMinionsKilled : 70, Kills : 2, Deaths : 1, Assists : 5, ", "14": "Current-Gold : 836, Level : 9, CS : 15, Total-Gold : 5486, JungleMinionsKilled : 78, Kills : 2, Deaths : 1, Assists : 5, ", "15": "Current-Gold : 339, Level : 10, CS : 18, Total-Gold : 5854, JungleMinionsKilled : 86, Kills : 2, Deaths : 1, Assists : 7, ", "16": "Current-Gold : 401, Level : 10, CS : 18, Total-Gold : 5916, JungleMinionsKilled : 86, Kills : 2, Deaths : 2, Assists : 7, "}}}}}, "participant_9": {"role_SUPPORT": {"teamId_200": {"position_TOP": {"minutes": {"0": "Current-Gold : 500, Level : 1, CS : 0, Total-Gold : 500, JungleMinionsKilled : 0, Kills : 0, Deaths : 0, Assists : 0, ", "1": "Current-Gold : 0, Level : 1, CS : 0, Total-Gold : 500, JungleMinionsKilled : 0, Kills : 0, Deaths : 0, Assists : 0, ", "2": "Current-Gold : 84, Level : 1, CS : 3, Total-Gold : 584, JungleMinionsKilled : 0, Kills : 0, Deaths : 0, Assists : 0, ", "3": "Current-Gold : 25, Level : 3, CS : 10, Total-Gold : 1125, JungleMinionsKilled : 0, Kills : 0, Deaths : 0, Assists : 0, ", "4": "Current-Gold : 163, Level : 3, CS : 11, Total-Gold : 1263, JungleMinionsKilled : 0, Kills : 1, Deaths : 1, Assists : 0, ", "5": "Current-Gold : 519, Level : 4, CS : 21, Total-Gold : 1619, JungleMinionsKilled : 0, Kills : 1, Deaths : 2, Assists : 0, ", "6": "Current-Gold : 379, Level : 4, CS : 23, Total-Gold : 1779, JungleMinionsKilled : 0, Kills : 1, Deaths : 2, Assists : 0, ", "7": "Current-Gold : 247, Level : 5, CS : 27, Total-Gold : 1997, JungleMinionsKilled : 2, Kills : 1, Deaths : 3, Assists : 0, ", "8": "Current-Gold : 113, Level : 5, CS : 29, Total-Gold : 2163, JungleMinionsKilled : 2, Kills : 1, Deaths : 3, Assists : 0, ", "9": "Current-Gold : 561, Level : 6, CS : 44, Total-Gold : 2611, JungleMinionsKilled : 2, Kills : 1, Deaths : 3, Assists : 0, ", "10": "Current-Gold : 757, Level : 6, CS : 48, Total-Gold : 2807, JungleMinionsKilled : 2, Kills : 1, Deaths : 3, Assists : 0, ", "11": "Current-Gold : 130, Level : 7, CS : 48, Total-Gold : 2930, JungleMinionsKilled : 2, Kills : 1, Deaths : 3, Assists : 0, ", "12": "Current-Gold : 341, Level : 7, CS : 53, Total-Gold : 3141, JungleMinionsKilled : 2, Kills : 1, Deaths : 5, Assists : 0, ", "13": "Current-Gold : 653, Level : 7, CS : 60, Total-Gold : 3453, JungleMinionsKilled : 2, Kills : 1, Deaths : 6, Assists : 0, ", "14": "Current-Gold : 821, Level : 7, CS : 63, Total-Gold : 3621, JungleMinionsKilled : 2, Kills : 1, Deaths : 7, Assists : 0, ", "15": "Current-Gold : 1133, Level : 8, CS : 72, Total-Gold : 3938, JungleMinionsKilled : 2, Kills : 1, Deaths : 7, Assists : 0, ", "16": "Current-Gold : 1245, Level : 8, CS : 72, Total-Gold : 4050, JungleMinionsKilled : 2, Kills : 1, Deaths : 7, Assists : 0, "}}}}}, "participant_10": {"role_DUO": {"teamId_200": {"position_BOTTOM": {"minutes": {"0": "Current-Gold : 500, Level : 1, CS : 0, Total-Gold : 500, JungleMinionsKilled : 0, Kills : 0, Deaths : 0, Assists : 0, ", "1": "Current-Gold : 0, Level : 1, CS : 0, Total-Gold : 500, JungleMinionsKilled : 0, Kills : 0, Deaths : 0, Assists : 0, ", "2": "Current-Gold : 63, Level : 1, CS : 2, Total-Gold : 563, JungleMinionsKilled : 0, Kills : 0, Deaths : 0, Assists : 0, ", "3": "Current-Gold : 455, Level : 2, CS : 15, Total-Gold : 955, JungleMinionsKilled : 0, Kills : 0, Deaths : 0, Assists : 0, ", "4": "Current-Gold : 103, Level : 3, CS : 21, Total-Gold : 1183, JungleMinionsKilled : 0, Kills : 0, Deaths : 0, Assists : 0, ", "5": "Current-Gold : 526, Level : 4, CS : 35, Total-Gold : 1606, JungleMinionsKilled : 0, Kills : 0, Deaths : 0, Assists : 0, ", "6": "Current-Gold : 95, Level : 5, CS : 40, Total-Gold : 1825, JungleMinionsKilled : 0, Kills : 0, Deaths : 0, Assists : 0, ", "7": "Current-Gold : 507, Level : 6, CS : 54, Total-Gold : 2237, JungleMinionsKilled : 0, Kills : 0, Deaths : 1, Assists : 0, ", "8": "Current-Gold : 139, Level : 6, CS : 57, Total-Gold : 2969, JungleMinionsKilled : 0, Kills : 0, Deaths : 1, Assists : 0, ", "9": "Current-Gold : 169, Level : 7, CS : 66, Total-Gold : 3549, JungleMinionsKilled : 0, Kills : 1, Deaths : 2, Assists : 2, ", "10": "Current-Gold : 610, Level : 7, CS : 77, Total-Gold : 3990, JungleMinionsKilled : 0, Kills : 2, Deaths : 3, Assists : 2, ", "11": "Current-Gold : 1139, Level : 8, CS : 89, Total-Gold : 4524, JungleMinionsKilled : 0, Kills : 2, Deaths : 3, Assists : 2, ", "12": "Current-Gold : 1607, Level : 9, CS : 94, Total-Gold : 4992, JungleMinionsKilled : 0, Kills : 2, Deaths : 3, Assists : 3, ", "13": "Current-Gold : 197, Level : 9, CS : 98, Total-Gold : 5182, JungleMinionsKilled : 0, Kills : 2, Deaths : 3, Assists : 3, ", "14": "Current-Gold : 1626, Level : 10, CS : 118, Total-Gold : 6611, JungleMinionsKilled : 0, Kills : 2, Deaths : 3, Assists : 3, ", "15": "Current-Gold : 601, Level : 10, CS : 128, Total-Gold : 7326, JungleMinionsKilled : 0, Kills : 4, Deaths : 3, Assists : 3, ", "16": "Current-Gold : 983, Level : 10, CS : 128, Total-Gold : 7708, JungleMinionsKilled : 0, Kills : 4, Deaths : 3, Assists : 3, "}}}}}}}